openworkflows/__init__.py
openworkflows/context.py
openworkflows/handles.py
openworkflows/node.py
openworkflows/parameters.py
openworkflows/registry.py
openworkflows/schema.py
openworkflows/workflow.py
openworkflows/nodes/__init__.py
openworkflows/nodes/audio.py
openworkflows/nodes/http.py
openworkflows/nodes/input.py
openworkflows/nodes/llm.py
openworkflows/nodes/output.py
openworkflows/nodes/transform.py
openworkflows/providers/__init__.py
openworkflows/providers/base.py
openworkflows/providers/litellm_engine.py
openworkflows/providers/mock.py
openworkflows/utils/__init__.py
openworkflows-0.1.1.dist-info/METADATA
openworkflows-0.1.1.dist-info/WHEEL
openworkflows-0.1.1.dist-info/RECORD
