Metadata-Version: 2.4
Name: openworkflows
Version: 0.1.1
Summary: A simple, developer-friendly Python package for creating AI workflows
Requires-Python: >=3.8
Requires-Dist: async-generator>=1.10
Requires-Dist: httpx>=0.28.1
Requires-Dist: litellm>=1.77.5
Requires-Dist: nemo-toolkit[asr]>=1.23.0
Requires-Dist: pydantic>=2.0.0
Requires-Dist: torch>=2.5.1
Requires-Dist: transformers>=4.46.3
Provides-Extra: audio
Requires-Dist: insanely-fast-whisper>=0.0.15; extra == 'audio'
Provides-Extra: dev
Requires-Dist: black>=23.0.0; extra == 'dev'
Requires-Dist: mypy>=1.0.0; extra == 'dev'
Requires-Dist: pytest-asyncio>=0.21.0; extra == 'dev'
Requires-Dist: pytest>=7.0.0; extra == 'dev'
Requires-Dist: ruff>=0.1.0; extra == 'dev'
Provides-Extra: llm
Requires-Dist: anthropic>=0.18.0; extra == 'llm'
Requires-Dist: litellm>=1.0.0; extra == 'llm'
Requires-Dist: openai>=1.0.0; extra == 'llm'
